Default/__init__.py
Default/mappings.json
Default/mappings.py
Default/settings.py
fhirparser/__init__.py
fhirparser/fhirclass.py
fhirparser/fhirloader.py
fhirparser/fhirrenderer.py
fhirparser/fhirspec.py
fhirparser/fhirunittest.py
fhirparser/generate.py
fhirparser/logger.py
fhirparser-0.4.0.dist-info/AUTHORS
fhirparser-0.4.0.dist-info/LICENSE.txt
fhirparser-0.4.0.dist-info/METADATA
fhirparser-0.4.0.dist-info/WHEEL
fhirparser-0.4.0.dist-info/entry_points.txt
fhirparser-0.4.0.dist-info/pbr.json
fhirparser-0.4.0.dist-info/top_level.txt
fhirparser-0.4.0.dist-info/RECORD
