Metadata-Version: 2.1
Name: fhirparser
Version: 0.4.0
Summary: FHIR StructureDefinition Parsing tool
Home-page: https://github.com/smart-on-fhir/fhir-parser/
Author: Pascal Pfiffner
Author-email: pp2@me.com
License: Apache License, Version 2.0
Keywords: fhir,parser
Platform: UNKNOWN
Classifier: Development Status :: 4 - Beta
Classifier: Environment :: Console
Classifier: Intended Audience :: Developers
Classifier: Intended Audience :: Science/Research
Classifier: Intended Audience :: Healthcare Industry
Classifier: License :: OSI Approved :: Apache Software License
Classifier: Programming Language :: Python :: 3 :: Only
Classifier: Programming Language :: Python :: 3.7
Requires-Python: >=3.7
Requires-Dist: colorlog (>=4.0.2)
Requires-Dist: crefi
Requires-Dist: jinja2 (>=2.10.3)
Requires-Dist: markupsafe (>=1.1.1)
Requires-Dist: rdflib (>=4.2.2)
Requires-Dist: requests (>=2.22.0)
